{
  "schemaVersion": "1.0.0",
  "ledgerId": "results-as-of-2026-06-29-after-match-073",
  "asOf": "2026-06-29T07:02:22.483Z",
  "sourcePolicy": "provider-public-delayed",
  "notes": "Derived from the sanitized provider-derived live-state (sourceObjectPath live-state.provider.sanitized.json), generated from a committed public-safe reference fixture (read mode: file fixture, not Blob). Locks all 72 group-stage matches plus the completed Round of 32 match M73 (Canada over South Africa). Provider had 73 completed official matches total.",
  "sourceObjectPath": "live-state.provider.sanitized.json",
  "providerCompletedMatchesTotal": 73,
  "results": [
    {
      "matchNumber": 1,
      "stage": "group",
      "group": "A",
      "homeTeamId": "mexico",
      "awayTeamId": "south-africa",
      "homeGoals": 2,
      "awayGoals": 0,
      "status": "complete",
      "playedAt": "2026-06-11T19:00:00Z"
    },
    {
      "matchNumber": 2,
      "stage": "group",
      "group": "A",
      "homeTeamId": "south-korea",
      "awayTeamId": "czechia",
      "homeGoals": 2,
      "awayGoals": 1,
      "status": "complete",
      "playedAt": "2026-06-12T02:00:00Z"
    },
    {
      "matchNumber": 3,
      "stage": "group",
      "group": "B",
      "homeTeamId": "canada",
      "awayTeamId": "bosnia-herzegovina",
      "homeGoals": 1,
      "awayGoals": 1,
      "status": "complete",
      "playedAt": "2026-06-12T19:00:00Z"
    },
    {
      "matchNumber": 4,
      "stage": "group",
      "group": "D",
      "homeTeamId": "usa",
      "awayTeamId": "paraguay",
      "homeGoals": 4,
      "awayGoals": 1,
      "status": "complete",
      "playedAt": "2026-06-13T01:00:00Z"
    },
    {
      "matchNumber": 5,
      "stage": "group",
      "group": "C",
      "homeTeamId": "haiti",
      "awayTeamId": "scotland",
      "homeGoals": 0,
      "awayGoals": 1,
      "status": "complete",
      "playedAt": "2026-06-14T01:00:00Z"
    },
    {
      "matchNumber": 6,
      "stage": "group",
      "group": "D",
      "homeTeamId": "australia",
      "awayTeamId": "turkiye",
      "homeGoals": 2,
      "awayGoals": 0,
      "status": "complete",
      "playedAt": "2026-06-14T04:00:00Z"
    },
    {
      "matchNumber": 7,
      "stage": "group",
      "group": "C",
      "homeTeamId": "brazil",
      "awayTeamId": "morocco",
      "homeGoals": 1,
      "awayGoals": 1,
      "status": "complete",
      "playedAt": "2026-06-13T22:00:00Z"
    },
    {
      "matchNumber": 8,
      "stage": "group",
      "group": "B",
      "homeTeamId": "qatar",
      "awayTeamId": "switzerland",
      "homeGoals": 1,
      "awayGoals": 1,
      "status": "complete",
      "playedAt": "2026-06-13T19:00:00Z"
    },
    {
      "matchNumber": 9,
      "stage": "group",
      "group": "E",
      "homeTeamId": "ivory-coast",
      "awayTeamId": "ecuador",
      "homeGoals": 1,
      "awayGoals": 0,
      "status": "complete",
      "playedAt": "2026-06-14T23:00:00Z"
    },
    {
      "matchNumber": 10,
      "stage": "group",
      "group": "E",
      "homeTeamId": "germany",
      "awayTeamId": "curacao",
      "homeGoals": 7,
      "awayGoals": 1,
      "status": "complete",
      "playedAt": "2026-06-14T17:00:00Z"
    },
    {
      "matchNumber": 11,
      "stage": "group",
      "group": "F",
      "homeTeamId": "netherlands",
      "awayTeamId": "japan",
      "homeGoals": 2,
      "awayGoals": 2,
      "status": "complete",
      "playedAt": "2026-06-14T20:00:00Z"
    },
    {
      "matchNumber": 12,
      "stage": "group",
      "group": "F",
      "homeTeamId": "sweden",
      "awayTeamId": "tunisia",
      "homeGoals": 5,
      "awayGoals": 1,
      "status": "complete",
      "playedAt": "2026-06-15T02:00:00Z"
    },
    {
      "matchNumber": 13,
      "stage": "group",
      "group": "H",
      "homeTeamId": "saudi-arabia",
      "awayTeamId": "uruguay",
      "homeGoals": 1,
      "awayGoals": 1,
      "status": "complete",
      "playedAt": "2026-06-15T22:00:00Z"
    },
    {
      "matchNumber": 14,
      "stage": "group",
      "group": "H",
      "homeTeamId": "spain",
      "awayTeamId": "cape-verde",
      "homeGoals": 0,
      "awayGoals": 0,
      "status": "complete",
      "playedAt": "2026-06-15T16:00:00Z"
    },
    {
      "matchNumber": 15,
      "stage": "group",
      "group": "G",
      "homeTeamId": "iran",
      "awayTeamId": "new-zealand",
      "homeGoals": 2,
      "awayGoals": 2,
      "status": "complete",
      "playedAt": "2026-06-16T01:00:00Z"
    },
    {
      "matchNumber": 16,
      "stage": "group",
      "group": "G",
      "homeTeamId": "belgium",
      "awayTeamId": "egypt",
      "homeGoals": 1,
      "awayGoals": 1,
      "status": "complete",
      "playedAt": "2026-06-15T19:00:00Z"
    },
    {
      "matchNumber": 17,
      "stage": "group",
      "group": "I",
      "homeTeamId": "france",
      "awayTeamId": "senegal",
      "homeGoals": 3,
      "awayGoals": 1,
      "status": "complete",
      "playedAt": "2026-06-16T19:00:00Z"
    },
    {
      "matchNumber": 18,
      "stage": "group",
      "group": "I",
      "homeTeamId": "iraq",
      "awayTeamId": "norway",
      "homeGoals": 1,
      "awayGoals": 4,
      "status": "complete",
      "playedAt": "2026-06-16T22:00:00Z"
    },
    {
      "matchNumber": 19,
      "stage": "group",
      "group": "J",
      "homeTeamId": "argentina",
      "awayTeamId": "algeria",
      "homeGoals": 3,
      "awayGoals": 0,
      "status": "complete",
      "playedAt": "2026-06-17T01:00:00Z"
    },
    {
      "matchNumber": 20,
      "stage": "group",
      "group": "J",
      "homeTeamId": "austria",
      "awayTeamId": "jordan",
      "homeGoals": 3,
      "awayGoals": 1,
      "status": "complete",
      "playedAt": "2026-06-17T04:00:00Z"
    },
    {
      "matchNumber": 21,
      "stage": "group",
      "group": "L",
      "homeTeamId": "ghana",
      "awayTeamId": "panama",
      "homeGoals": 1,
      "awayGoals": 0,
      "status": "complete",
      "playedAt": "2026-06-17T23:00:00Z"
    },
    {
      "matchNumber": 22,
      "stage": "group",
      "group": "L",
      "homeTeamId": "england",
      "awayTeamId": "croatia",
      "homeGoals": 4,
      "awayGoals": 2,
      "status": "complete",
      "playedAt": "2026-06-17T20:00:00Z"
    },
    {
      "matchNumber": 23,
      "stage": "group",
      "group": "K",
      "homeTeamId": "portugal",
      "awayTeamId": "congo-dr",
      "homeGoals": 1,
      "awayGoals": 1,
      "status": "complete",
      "playedAt": "2026-06-17T17:00:00Z"
    },
    {
      "matchNumber": 24,
      "stage": "group",
      "group": "K",
      "homeTeamId": "uzbekistan",
      "awayTeamId": "colombia",
      "homeGoals": 1,
      "awayGoals": 3,
      "status": "complete",
      "playedAt": "2026-06-18T02:00:00Z"
    },
    {
      "matchNumber": 25,
      "stage": "group",
      "group": "A",
      "homeTeamId": "czechia",
      "awayTeamId": "south-africa",
      "homeGoals": 1,
      "awayGoals": 1,
      "status": "complete",
      "playedAt": "2026-06-18T16:00:00Z"
    },
    {
      "matchNumber": 26,
      "stage": "group",
      "group": "B",
      "homeTeamId": "switzerland",
      "awayTeamId": "bosnia-herzegovina",
      "homeGoals": 4,
      "awayGoals": 1,
      "status": "complete",
      "playedAt": "2026-06-18T19:00:00Z"
    },
    {
      "matchNumber": 27,
      "stage": "group",
      "group": "B",
      "homeTeamId": "canada",
      "awayTeamId": "qatar",
      "homeGoals": 6,
      "awayGoals": 0,
      "status": "complete",
      "playedAt": "2026-06-18T22:00:00Z"
    },
    {
      "matchNumber": 28,
      "stage": "group",
      "group": "A",
      "homeTeamId": "mexico",
      "awayTeamId": "south-korea",
      "homeGoals": 1,
      "awayGoals": 0,
      "status": "complete",
      "playedAt": "2026-06-19T01:00:00Z"
    },
    {
      "matchNumber": 29,
      "stage": "group",
      "group": "C",
      "homeTeamId": "brazil",
      "awayTeamId": "haiti",
      "homeGoals": 3,
      "awayGoals": 0,
      "status": "complete",
      "playedAt": "2026-06-20T00:30:00Z"
    },
    {
      "matchNumber": 30,
      "stage": "group",
      "group": "C",
      "homeTeamId": "scotland",
      "awayTeamId": "morocco",
      "homeGoals": 0,
      "awayGoals": 1,
      "status": "complete",
      "playedAt": "2026-06-19T22:00:00Z"
    },
    {
      "matchNumber": 31,
      "stage": "group",
      "group": "D",
      "homeTeamId": "turkiye",
      "awayTeamId": "paraguay",
      "homeGoals": 0,
      "awayGoals": 1,
      "status": "complete",
      "playedAt": "2026-06-20T03:00:00Z"
    },
    {
      "matchNumber": 32,
      "stage": "group",
      "group": "D",
      "homeTeamId": "usa",
      "awayTeamId": "australia",
      "homeGoals": 2,
      "awayGoals": 0,
      "status": "complete",
      "playedAt": "2026-06-19T19:00:00Z"
    },
    {
      "matchNumber": 33,
      "stage": "group",
      "group": "E",
      "homeTeamId": "germany",
      "awayTeamId": "ivory-coast",
      "homeGoals": 2,
      "awayGoals": 1,
      "status": "complete",
      "playedAt": "2026-06-20T20:00:00Z"
    },
    {
      "matchNumber": 34,
      "stage": "group",
      "group": "E",
      "homeTeamId": "ecuador",
      "awayTeamId": "curacao",
      "homeGoals": 0,
      "awayGoals": 0,
      "status": "complete",
      "playedAt": "2026-06-21T00:00:00Z"
    },
    {
      "matchNumber": 35,
      "stage": "group",
      "group": "F",
      "homeTeamId": "netherlands",
      "awayTeamId": "sweden",
      "homeGoals": 5,
      "awayGoals": 1,
      "status": "complete",
      "playedAt": "2026-06-20T17:00:00Z"
    },
    {
      "matchNumber": 36,
      "stage": "group",
      "group": "F",
      "homeTeamId": "tunisia",
      "awayTeamId": "japan",
      "homeGoals": 0,
      "awayGoals": 4,
      "status": "complete",
      "playedAt": "2026-06-21T04:00:00Z"
    },
    {
      "matchNumber": 37,
      "stage": "group",
      "group": "H",
      "homeTeamId": "uruguay",
      "awayTeamId": "cape-verde",
      "homeGoals": 2,
      "awayGoals": 2,
      "status": "complete",
      "playedAt": "2026-06-21T22:00:00Z"
    },
    {
      "matchNumber": 38,
      "stage": "group",
      "group": "H",
      "homeTeamId": "spain",
      "awayTeamId": "saudi-arabia",
      "homeGoals": 4,
      "awayGoals": 0,
      "status": "complete",
      "playedAt": "2026-06-21T16:00:00Z"
    },
    {
      "matchNumber": 39,
      "stage": "group",
      "group": "G",
      "homeTeamId": "belgium",
      "awayTeamId": "iran",
      "homeGoals": 0,
      "awayGoals": 0,
      "status": "complete",
      "playedAt": "2026-06-21T19:00:00Z"
    },
    {
      "matchNumber": 40,
      "stage": "group",
      "group": "G",
      "homeTeamId": "new-zealand",
      "awayTeamId": "egypt",
      "homeGoals": 1,
      "awayGoals": 3,
      "status": "complete",
      "playedAt": "2026-06-22T01:00:00Z"
    },
    {
      "matchNumber": 41,
      "stage": "group",
      "group": "I",
      "homeTeamId": "norway",
      "awayTeamId": "senegal",
      "homeGoals": 3,
      "awayGoals": 2,
      "status": "complete",
      "playedAt": "2026-06-23T00:00:00Z"
    },
    {
      "matchNumber": 42,
      "stage": "group",
      "group": "I",
      "homeTeamId": "france",
      "awayTeamId": "iraq",
      "homeGoals": 3,
      "awayGoals": 0,
      "status": "complete",
      "playedAt": "2026-06-22T21:00:00Z"
    },
    {
      "matchNumber": 43,
      "stage": "group",
      "group": "J",
      "homeTeamId": "argentina",
      "awayTeamId": "austria",
      "homeGoals": 2,
      "awayGoals": 0,
      "status": "complete",
      "playedAt": "2026-06-22T17:00:00Z"
    },
    {
      "matchNumber": 44,
      "stage": "group",
      "group": "J",
      "homeTeamId": "jordan",
      "awayTeamId": "algeria",
      "homeGoals": 1,
      "awayGoals": 2,
      "status": "complete",
      "playedAt": "2026-06-23T03:00:00Z"
    },
    {
      "matchNumber": 45,
      "stage": "group",
      "group": "L",
      "homeTeamId": "england",
      "awayTeamId": "ghana",
      "homeGoals": 0,
      "awayGoals": 0,
      "status": "complete",
      "playedAt": "2026-06-23T20:00:00Z"
    },
    {
      "matchNumber": 46,
      "stage": "group",
      "group": "L",
      "homeTeamId": "panama",
      "awayTeamId": "croatia",
      "homeGoals": 0,
      "awayGoals": 1,
      "status": "complete",
      "playedAt": "2026-06-23T23:00:00Z"
    },
    {
      "matchNumber": 47,
      "stage": "group",
      "group": "K",
      "homeTeamId": "portugal",
      "awayTeamId": "uzbekistan",
      "homeGoals": 5,
      "awayGoals": 0,
      "status": "complete",
      "playedAt": "2026-06-23T17:00:00Z"
    },
    {
      "matchNumber": 48,
      "stage": "group",
      "group": "K",
      "homeTeamId": "colombia",
      "awayTeamId": "congo-dr",
      "homeGoals": 1,
      "awayGoals": 0,
      "status": "complete",
      "playedAt": "2026-06-24T02:00:00Z"
    },
    {
      "matchNumber": 49,
      "stage": "group",
      "group": "C",
      "homeTeamId": "scotland",
      "awayTeamId": "brazil",
      "homeGoals": 0,
      "awayGoals": 3,
      "status": "complete",
      "playedAt": "2026-06-24T22:00:00Z"
    },
    {
      "matchNumber": 50,
      "stage": "group",
      "group": "C",
      "homeTeamId": "morocco",
      "awayTeamId": "haiti",
      "homeGoals": 4,
      "awayGoals": 2,
      "status": "complete",
      "playedAt": "2026-06-24T22:00:00Z"
    },
    {
      "matchNumber": 51,
      "stage": "group",
      "group": "B",
      "homeTeamId": "switzerland",
      "awayTeamId": "canada",
      "homeGoals": 2,
      "awayGoals": 1,
      "status": "complete",
      "playedAt": "2026-06-24T19:00:00Z"
    },
    {
      "matchNumber": 52,
      "stage": "group",
      "group": "B",
      "homeTeamId": "bosnia-herzegovina",
      "awayTeamId": "qatar",
      "homeGoals": 3,
      "awayGoals": 1,
      "status": "complete",
      "playedAt": "2026-06-24T19:00:00Z"
    },
    {
      "matchNumber": 53,
      "stage": "group",
      "group": "A",
      "homeTeamId": "czechia",
      "awayTeamId": "mexico",
      "homeGoals": 0,
      "awayGoals": 3,
      "status": "complete",
      "playedAt": "2026-06-25T01:00:00Z"
    },
    {
      "matchNumber": 54,
      "stage": "group",
      "group": "A",
      "homeTeamId": "south-africa",
      "awayTeamId": "south-korea",
      "homeGoals": 1,
      "awayGoals": 0,
      "status": "complete",
      "playedAt": "2026-06-25T01:00:00Z"
    },
    {
      "matchNumber": 55,
      "stage": "group",
      "group": "E",
      "homeTeamId": "curacao",
      "awayTeamId": "ivory-coast",
      "homeGoals": 0,
      "awayGoals": 2,
      "status": "complete",
      "playedAt": "2026-06-25T20:00:00Z"
    },
    {
      "matchNumber": 56,
      "stage": "group",
      "group": "E",
      "homeTeamId": "ecuador",
      "awayTeamId": "germany",
      "homeGoals": 2,
      "awayGoals": 1,
      "status": "complete",
      "playedAt": "2026-06-25T20:00:00Z"
    },
    {
      "matchNumber": 57,
      "stage": "group",
      "group": "F",
      "homeTeamId": "japan",
      "awayTeamId": "sweden",
      "homeGoals": 1,
      "awayGoals": 1,
      "status": "complete",
      "playedAt": "2026-06-25T23:00:00Z"
    },
    {
      "matchNumber": 58,
      "stage": "group",
      "group": "F",
      "homeTeamId": "tunisia",
      "awayTeamId": "netherlands",
      "homeGoals": 1,
      "awayGoals": 3,
      "status": "complete",
      "playedAt": "2026-06-25T23:00:00Z"
    },
    {
      "matchNumber": 59,
      "stage": "group",
      "group": "D",
      "homeTeamId": "turkiye",
      "awayTeamId": "usa",
      "homeGoals": 3,
      "awayGoals": 2,
      "status": "complete",
      "playedAt": "2026-06-26T02:00:00Z"
    },
    {
      "matchNumber": 60,
      "stage": "group",
      "group": "D",
      "homeTeamId": "paraguay",
      "awayTeamId": "australia",
      "homeGoals": 0,
      "awayGoals": 0,
      "status": "complete",
      "playedAt": "2026-06-26T02:00:00Z"
    },
    {
      "matchNumber": 61,
      "stage": "group",
      "group": "I",
      "homeTeamId": "norway",
      "awayTeamId": "france",
      "homeGoals": 1,
      "awayGoals": 4,
      "status": "complete",
      "playedAt": "2026-06-26T19:00:00Z"
    },
    {
      "matchNumber": 62,
      "stage": "group",
      "group": "I",
      "homeTeamId": "senegal",
      "awayTeamId": "iraq",
      "homeGoals": 5,
      "awayGoals": 0,
      "status": "complete",
      "playedAt": "2026-06-26T19:00:00Z"
    },
    {
      "matchNumber": 63,
      "stage": "group",
      "group": "G",
      "homeTeamId": "egypt",
      "awayTeamId": "iran",
      "homeGoals": 1,
      "awayGoals": 1,
      "status": "complete",
      "playedAt": "2026-06-27T03:00:00Z"
    },
    {
      "matchNumber": 64,
      "stage": "group",
      "group": "G",
      "homeTeamId": "new-zealand",
      "awayTeamId": "belgium",
      "homeGoals": 1,
      "awayGoals": 5,
      "status": "complete",
      "playedAt": "2026-06-27T03:00:00Z"
    },
    {
      "matchNumber": 65,
      "stage": "group",
      "group": "H",
      "homeTeamId": "cape-verde",
      "awayTeamId": "saudi-arabia",
      "homeGoals": 0,
      "awayGoals": 0,
      "status": "complete",
      "playedAt": "2026-06-27T00:00:00Z"
    },
    {
      "matchNumber": 66,
      "stage": "group",
      "group": "H",
      "homeTeamId": "uruguay",
      "awayTeamId": "spain",
      "homeGoals": 0,
      "awayGoals": 1,
      "status": "complete",
      "playedAt": "2026-06-27T00:00:00Z"
    },
    {
      "matchNumber": 67,
      "stage": "group",
      "group": "L",
      "homeTeamId": "panama",
      "awayTeamId": "england",
      "homeGoals": 0,
      "awayGoals": 2,
      "status": "complete",
      "playedAt": "2026-06-27T21:00:00Z"
    },
    {
      "matchNumber": 68,
      "stage": "group",
      "group": "L",
      "homeTeamId": "croatia",
      "awayTeamId": "ghana",
      "homeGoals": 2,
      "awayGoals": 1,
      "status": "complete",
      "playedAt": "2026-06-27T21:00:00Z"
    },
    {
      "matchNumber": 69,
      "stage": "group",
      "group": "J",
      "homeTeamId": "algeria",
      "awayTeamId": "austria",
      "homeGoals": 3,
      "awayGoals": 3,
      "status": "complete",
      "playedAt": "2026-06-28T02:00:00Z"
    },
    {
      "matchNumber": 70,
      "stage": "group",
      "group": "J",
      "homeTeamId": "jordan",
      "awayTeamId": "argentina",
      "homeGoals": 1,
      "awayGoals": 3,
      "status": "complete",
      "playedAt": "2026-06-28T02:00:00Z"
    },
    {
      "matchNumber": 71,
      "stage": "group",
      "group": "K",
      "homeTeamId": "colombia",
      "awayTeamId": "portugal",
      "homeGoals": 0,
      "awayGoals": 0,
      "status": "complete",
      "playedAt": "2026-06-27T23:30:00Z"
    },
    {
      "matchNumber": 72,
      "stage": "group",
      "group": "K",
      "homeTeamId": "congo-dr",
      "awayTeamId": "uzbekistan",
      "homeGoals": 3,
      "awayGoals": 1,
      "status": "complete",
      "playedAt": "2026-06-27T23:30:00Z"
    },
    {
      "matchNumber": 73,
      "stage": "roundOf32",
      "homeTeamId": "south-africa",
      "awayTeamId": "canada",
      "homeGoals": 0,
      "awayGoals": 1,
      "status": "complete",
      "winnerTeamId": "canada",
      "playedAt": "2026-06-28T19:00:00Z"
    }
  ]
}
